secret/SCRATCH.py
secret/__init__.py
tests/__init__.py
tests/__main__.py
threadom/__init__.py
threadom/__main__.py
threadom/hooking/__init__.py
threadom/hooking/ante_build_hook.py
threadom/hooking/ante_release_hook.py
threadom/hooking/post_build_hook.py
threadom/hooking/post_release_hook.py
threadom/pyrustic_data/hooking.json
threadom/pyrustic_data/hubstore.json
threadom/pyrustic_data/release_info.json
threadom/pyrustic_data/backstage/config/build.json
threadom/pyrustic_data/backstage/config/init.json
threadom/pyrustic_data/backstage/config/release.json
threadom/pyrustic_data/backstage/data/build_report.json
threadom/pyrustic_data/backstage/data/github_release_form.json
threadom/pyrustic_data/backstage/hooking/build.json
threadom/pyrustic_data/backstage/hooking/init.json
threadom/pyrustic_data/backstage/hooking/release.json
threadom/pyrustic_data/backstage/report/build_report.json
threadom/pyrustic_data/backstage/report/release_report.json
threadom/pyrustic_data/hubstore/img.json
threadom/pyrustic_data/hubstore/promotion.json
threadom-0.0.7.dist-info/LICENSE
threadom-0.0.7.dist-info/METADATA
threadom-0.0.7.dist-info/WHEEL
threadom-0.0.7.dist-info/entry_points.txt
threadom-0.0.7.dist-info/top_level.txt
threadom-0.0.7.dist-info/RECORD
