Metadata-Version: 2.1
Name: threadom
Version: 0.0.7
Summary: Tkinter-compatible multithreading
Home-page: https://github.com/pyrustic/threadom
Author: Pyrustic Evangelist
Author-email: rusticalex@yahoo.com
Maintainer: Pyrustic Evangelist
Maintainer-email: rusticalex@yahoo.com
License: MIT
Keywords: library,tkinter-multithreading,multithreading,gui-multithreading,tkinter,lightweight,pyrustic
Platform: UNKNOWN
Classifier: Programming Language :: Python :: 3
Classifier: License :: OSI Approved :: MIT License
Classifier: Operating System :: OS Independent
Requires-Python: >=3.5
License-File: LICENSE
